bamengine/__init__.py
bamengine/economy.py
bamengine/logging.py
bamengine/logging.pyi
bamengine/ops.py
bamengine/py.typed
bamengine/results.py
bamengine/simulation.py
bamengine/typing.py
bamengine/utils.py
bamengine/config/__init__.py
bamengine/config/default_pipeline.yml
bamengine/config/defaults.yml
bamengine/config/schema.py
bamengine/config/validator.py
bamengine/core/__init__.py
bamengine/core/agent.py
bamengine/core/decorators.py
bamengine/core/event.py
bamengine/core/pipeline.py
bamengine/core/registry.py
bamengine/core/relationship.py
bamengine/core/role.py
bamengine/events/__init__.py
bamengine/events/bankruptcy.py
bamengine/events/credit_market.py
bamengine/events/economy_stats.py
bamengine/events/goods_market.py
bamengine/events/labor_market.py
bamengine/events/planning.py
bamengine/events/production.py
bamengine/events/revenue.py
bamengine/events/_internal/__init__.py
bamengine/events/_internal/bankruptcy.py
bamengine/events/_internal/credit_market.py
bamengine/events/_internal/goods_market.py
bamengine/events/_internal/labor_market.py
bamengine/events/_internal/planning.py
bamengine/events/_internal/production.py
bamengine/events/_internal/revenue.py
bamengine/relationships/__init__.py
bamengine/relationships/loanbook.py
bamengine/roles/__init__.py
bamengine/roles/borrower.py
bamengine/roles/consumer.py
bamengine/roles/employer.py
bamengine/roles/lender.py
bamengine/roles/producer.py
bamengine/roles/worker.py
bamengine-0.2.1.dist-info/licenses/LICENSE
bamengine-0.2.1.dist-info/METADATA
bamengine-0.2.1.dist-info/WHEEL
bamengine-0.2.1.dist-info/top_level.txt
bamengine-0.2.1.dist-info/RECORD
