Metadata-Version: 2.4
Name: bamengine
Version: 0.2.1
Summary: High-performance agent-based framework for the BAM macroeconomic model
Author-email: Kostas Ganitis <ganitiskostas@gmail.com>
Maintainer-email: Kostas Ganitis <ganitiskostas@gmail.com>
License-Expression: MIT
Project-URL: homepage, https://bam-engine.readthedocs.io/
Project-URL: source, https://github.com/kganitis/bam-engine
Project-URL: tracker, https://github.com/kganitis/bam-engine/issues
Project-URL: changelog, https://bam-engine.readthedocs.io/en/latest/changelog.html
Keywords: agent-based-modeling,macroeconomics,economic-simulation,computational-economics,complex-adaptive-systems,heterogeneous-agents,entity-component-system,simulation,scientific-computing,bam-model
Classifier: Development Status :: 3 - Alpha
Classifier: Intended Audience :: Science/Research
Classifier: Intended Audience :: Financial and Insurance Industry
Classifier: Intended Audience :: Education
Classifier: Natural Language :: English
Classifier: Operating System :: OS Independent
Classifier: Programming Language :: Python :: 3
Classifier: Programming Language :: Python :: 3.11
Classifier: Programming Language :: Python :: 3.12
Classifier: Programming Language :: Python :: 3.13
Classifier: Topic :: Scientific/Engineering
Classifier: Topic :: Office/Business :: Financial
Classifier: Typing :: Typed
Requires-Python: >=3.11
License-File: LICENSE
Requires-Dist: numpy>=1.26
Requires-Dist: PyYAML>=6.0.2
Provides-Extra: pandas
Requires-Dist: pandas>=2.0; extra == "pandas"
Provides-Extra: dev
Requires-Dist: bamengine[docs,lint,pandas,test]; extra == "dev"
Requires-Dist: nox>=2024.3.2; extra == "dev"
Provides-Extra: test
Requires-Dist: bamengine[pandas]; extra == "test"
Requires-Dist: pytest>=8.3; extra == "test"
Requires-Dist: pytest-cov>=5.0; extra == "test"
Requires-Dist: hypothesis>=6.131.9; extra == "test"
Requires-Dist: pytest-benchmark>=4.0.0; extra == "test"
Requires-Dist: snakeviz>=2.2.0; extra == "test"
Requires-Dist: scipy>=1.11; extra == "test"
Provides-Extra: lint
Requires-Dist: ruff>=0.4; extra == "lint"
Requires-Dist: mypy>=1.9; extra == "lint"
Requires-Dist: types-PyYAML>=6.0; extra == "lint"
Requires-Dist: pandas-stubs>=2.0; extra == "lint"
Provides-Extra: docs
Requires-Dist: bamengine[pandas]; extra == "docs"
Requires-Dist: sphinx>=7.0; extra == "docs"
Requires-Dist: sphinx-gallery>=0.15.0; extra == "docs"
Requires-Dist: pydata-sphinx-theme>=0.15.0; extra == "docs"
Requires-Dist: matplotlib>=3.8; extra == "docs"
Requires-Dist: numpydoc>=1.6; extra == "docs"
Dynamic: license-file
